atypical/__init__.py
atypical/currency.py
atypical/email.py
atypical/money.py
atypical/phone.py
atypical/templated.py
atypical/url.py
atypical-0.4.0.dist-info/METADATA
atypical-0.4.0.dist-info/WHEEL
atypical-0.4.0.dist-info/licenses/LICENSE
atypical-0.4.0.dist-info/RECORD
